{
    "cultures": [
        {
            "title" : "Daivaradhane",
            "images" : [ "/assets/Home/swiper/daivaradhane1.webp" , "/assets/Home/swiper/daivaradhane2.jpeg" , "/assets/Home/swiper/daivaradhane3.jpg"],
            "descr" : "Daivaradhane is a sacred ritual of Tulunadu where divine spirits (Daivas) are invoked, worshipped, and embodied through possessed oracles, serving as intermediaries between gods and devotees."
        },
        {
            "title" : "Nagaradhane",
            "images" : ["/assets/Home/swiper/nagaradhane1.webp", "/assets/Home/swiper/nagaradhane2.jpg", "/assets/Home/swiper/nagaradhane3.jpg"],
            "descr" : "Nagaradhane is the sacred serpent worship of Tulunadu, where the Indian cobra (Nāga) is venerated as a divine protector, ensuring prosperity, fertility, and ancestral blessings."
        },
        {
            "title" : "Daivaradhane",
            "images" : [ "/assets/Home/swiper/daivaradhane1.webp" , "/assets/Home/swiper/daivaradhane2.jpeg" , "/assets/Home/swiper/daivaradhane3.jpg"],
            "descr" : "Daivaradhane is a sacred ritual of Tulunadu where divine spirits (Daivas) are invoked, worshipped, and embodied through possessed oracles, serving as intermediaries between gods and devotees."
        },
        {
            "title" : "Nagaradhane",
            "images" : ["/assets/Home/swiper/nagaradhane1.webp", "/assets/Home/swiper/nagaradhane2.jpg", "/assets/Home/swiper/nagaradhane3.jpg"],
            "descr" : "Nagaradhane is the sacred serpent worship of Tulunadu, where the Indian cobra (Nāga) is venerated as a divine protector, ensuring prosperity, fertility, and ancestral blessings."
        }
    ],

    "landmarks": [

        {
            "title" : "Malaraya",
            "descr" : "lorem ipsum dolor sit",
            "image" : "/assets/Home/recent/malaraya.JPG"
        },
        {
            "title" : "Jumadi",
            "descr" : "lorem ipsum dolor sit",
            "image" : "/assets/Home/recent/jumadi.jpg"
        },
        {
            "title" : "Kodamandaya",
            "descr" : "lorem ipsum dolor sit",
            "image" : "/assets/Home/recent/kodamandaya.jpg"
        },
        {
            "title" : "Panjurli",
            "descr" : "lorem ipsum dolor sit",
            "image" : "/assets/Home/recent/panjurli.jpg"
        },
        {
            "title" : "Pilichamundi",
            "descr" : "lorem ipsum dolor sit",
            "image" : "/assets/Home/recent/pilchandi.jpg"
        }
    ],

    "updates": [
        {
            "title" : "Malaraya",
            "descr" : "Lorem ipsum, dolor sit amet consectetur adipisicing elit. Porro, excepturi quaerat sequi quasi maiores at! Ab, quam perspiciatis sed maiores quasi minima quia ea rerum ad quae, recusandae ipsam commodi.",
            "images" : [ {"src" : "/assets/Home/recent/malaraya.JPG", "alt": "hi" }]
        },
        {
            "title" : "Malaraya",
            "descr" : "Lorem ipsum, dolor sit amet consectetur adipisicing elit. Porro, excepturi quaerat sequi quasi maiores at! Ab, quam perspiciatis sed maiores quasi minima quia ea rerum ad quae, recusandae ipsam commodi.",
            "images" : [ {"src" : "/assets/Home/recent/malaraya.JPG", "alt": "hi" }]
        },
        {
            "title" : "Malaraya",
            "descr" : "Lorem ipsum, dolor sit amet consectetur adipisicing elit. Porro, excepturi quaerat sequi quasi maiores at! Ab, quam perspiciatis sed maiores quasi minima quia ea rerum ad quae, recusandae ipsam commodi.",
            "images" : [ {"src" : "/assets/Home/recent/malaraya.JPG", "alt": "hi" }]
        },
        {
            "title" : "Malaraya",
            "descr" : "Lorem ipsum, dolor sit amet consectetur adipisicing elit. Porro, excepturi quaerat sequi quasi maiores at! Ab, quam perspiciatis sed maiores quasi minima quia ea rerum ad quae, recusandae ipsam commodi.",
            "images" : [ {"src" : "/assets/Home/recent/malaraya.JPG", "alt": "hi" }]
        },
        {
            "title" : "Malaraya",
            "descr" : "Lorem ipsum, dolor sit amet consectetur adipisicing elit. Porro, excepturi quaerat sequi quasi maiores at! Ab, quam perspiciatis sed maiores quasi minima quia ea rerum ad quae, recusandae ipsam commodi.",
            "images" : [ {"src" : "/assets/Home/recent/malaraya.JPG", "alt": "hi" }]
        },
        {
            "title" : "Malaraya",
            "descr" : "Lorem ipsum, dolor sit amet consectetur adipisicing elit. Porro, excepturi quaerat sequi quasi maiores at! Ab, quam perspiciatis sed maiores quasi minima quia ea rerum ad quae, recusandae ipsam commodi.",
            "images" : [ {"src" : "/assets/Home/recent/malaraya.JPG", "alt": "hi" }]
        },
        {
            "title" : "Malaraya",
            "descr" : "Lorem ipsum, dolor sit amet consectetur adipisicing elit. Porro, excepturi quaerat sequi quasi maiores at! Ab, quam perspiciatis sed maiores quasi minima quia ea rerum ad quae, recusandae ipsam commodi.",
            "images" : [ {"src" : "/assets/Home/recent/malaraya.JPG", "alt": "hi" }]
        },
        {
            "title" : "Malaraya",
            "descr" : "Lorem ipsum, dolor sit amet consectetur adipisicing elit. Porro, excepturi quaerat sequi quasi maiores at! Ab, quam perspiciatis sed maiores quasi minima quia ea rerum ad quae, recusandae ipsam commodi.",
            "images" : [ {"src" : "/assets/Home/recent/malaraya.JPG", "alt": "hi" }]
        },
        {
            "title" : "Malaraya",
            "descr" : "Lorem ipsum, dolor sit amet consectetur adipisicing elit. Porro, excepturi quaerat sequi quasi maiores at! Ab, quam perspiciatis sed maiores quasi minima quia ea rerum ad quae, recusandae ipsam commodi.",
            "images" : [ {"src" : "/assets/Home/recent/malaraya.JPG", "alt": "hi" }]
        },
        {
            "title" : "Malaraya",
            "descr" : "Lorem ipsum, dolor sit amet consectetur adipisicing elit. Porro, excepturi quaerat sequi quasi maiores at! Ab, quam perspiciatis sed maiores quasi minima quia ea rerum ad quae, recusandae ipsam commodi.",
            "images" : [ {"src" : "/assets/Home/recent/malaraya.JPG", "alt": "hi" }]
        },
        {
            "title" : "Malaraya",
            "descr" : "Lorem ipsum, dolor sit amet consectetur adipisicing elit. Porro, excepturi quaerat sequi quasi maiores at! Ab, quam perspiciatis sed maiores quasi minima quia ea rerum ad quae, recusandae ipsam commodi.",
            "images" : [ {"src" : "/assets/Home/recent/malaraya.JPG", "alt": "hi" }]
        },
        {
            "title" : "Malaraya",
            "descr" : "Lorem ipsum, dolor sit amet consectetur adipisicing elit. Porro, excepturi quaerat sequi quasi maiores at! Ab, quam perspiciatis sed maiores quasi minima quia ea rerum ad quae, recusandae ipsam commodi.",
            "images" : [ {"src" : "/assets/Home/recent/malaraya.JPG", "alt": "hi" }]
        },
        {
            "title" : "Malaraya",
            "descr" : "Lorem ipsum, dolor sit amet consectetur adipisicing elit. Porro, excepturi quaerat sequi quasi maiores at! Ab, quam perspiciatis sed maiores quasi minima quia ea rerum ad quae, recusandae ipsam commodi.",
            "images" : [ {"src" : "/assets/Home/recent/malaraya.JPG", "alt": "hi" }]
        },
        {
            "title" : "Malaraya",
            "descr" : "Lorem ipsum, dolor sit amet consectetur adipisicing elit. Porro, excepturi quaerat sequi quasi maiores at! Ab, quam perspiciatis sed maiores quasi minima quia ea rerum ad quae, recusandae ipsam commodi.",
            "images" : [ {"src" : "/assets/Home/recent/malaraya.JPG", "alt": "hi" }]
        },
        {
            "title" : "Malaraya",
            "descr" : "Lorem ipsum, dolor sit amet consectetur adipisicing elit. Porro, excepturi quaerat sequi quasi maiores at! Ab, quam perspiciatis sed maiores quasi minima quia ea rerum ad quae, recusandae ipsam commodi.",
            "images" : [ {"src" : "/assets/Home/recent/malaraya.JPG", "alt": "hi" }]
        },
        {
            "title" : "Malaraya",
            "descr" : "Lorem ipsum, dolor sit amet consectetur adipisicing elit. Porro, excepturi quaerat sequi quasi maiores at! Ab, quam perspiciatis sed maiores quasi minima quia ea rerum ad quae, recusandae ipsam commodi.",
            "images" : [ {"src" : "/assets/Home/recent/malaraya.JPG", "alt": "hi" }]
        },
        {
            "title" : "Malaraya",
            "descr" : "Lorem ipsum, dolor sit amet consectetur adipisicing elit. Porro, excepturi quaerat sequi quasi maiores at! Ab, quam perspiciatis sed maiores quasi minima quia ea rerum ad quae, recusandae ipsam commodi.",
            "images" : [ {"src" : "/assets/Home/recent/malaraya.JPG", "alt": "hi" }]
        },
        {
            "title" : "Malaraya",
            "descr" : "Lorem ipsum, dolor sit amet consectetur adipisicing elit. Porro, excepturi quaerat sequi quasi maiores at! Ab, quam perspiciatis sed maiores quasi minima quia ea rerum ad quae, recusandae ipsam commodi.",
            "images" : [ {"src" : "/assets/Home/recent/malaraya.JPG", "alt": "hi" }]
        }
    ],

  "explore": [
    {
      "title": "Daivaradhane",
      "descr": "Daivaradhane is a sacred ritual of Tulunadu where divine spirits (Daivas) are invoked, worshipped, and embodied through possessed oracles, serving as intermediaries between gods and devotees.",
      "image": "/assets/Explore/daivaradhane.jpg",
      "clipPathInitial": "polygon(0% 0%,0% 50%,0% 50%,0% 100%)",
      "clipPathNormal" : "polygon(0% 0%,100% 50%,100% 50%,0% 100%)",
      "clipPathFinal": "polygon(0% 0%,100% 0%,100% 100%,0% 100%)",
      "position": "center center",
      "placement": "left"
    },
    {
      "title": "Nagaradhane",
      "descr": "Nagaradhane is the sacred serpent worship of Tulunadu, where the Indian cobra (Nāga) is venerated as a divine protector, ensuring prosperity, fertility, and ancestral blessings.",
      "image": "/assets/Explore/nagaradhane.webp",
      "clipPathInitial": "polygon(100% 50%,100% 0%,100% 100%,100% 50%)",
      "clipPathNormal": "polygon(0% 50%,100% 0%,100% 100%,0% 50%)",
      "clipPathFinal": "polygon(0% 0%,100% 0%,100% 100%,0% 100%)",
      "position": "center center",
      "placement": "right"
    },
    {
      "title": "Yakshagana",
      "descr": "lorem ipsum dolor sit",
      "image": "/assets/Explore/yakshagana.webp",
      "clipPathInitial": "polygon(0% 0%,50% 0%,50% 0%,100% 0%)",
      "clipPathNormal" : "polygon(0% 0%,50% 100%,50% 100%,100% 0%)",
      "clipPathFinal": "polygon(0% 0%,0% 100%,100% 100%,100% 0%)",
      "position": "center 20%",
      "placement": "top"
    },
    {
      "title": "Kambala",
      "descr": "lorem ipsum dolor sit",
      "image": "/assets/Explore/kambala.webp",
      "clipPathInitial": "polygon(50% 100%,50% 100%,100% 100%,0% 100%)",
      "clipPathNormal": "polygon(50% 0%,50% 0%,100% 100%,0% 100%)",
      "clipPathFinal": "polygon(0% 0%,100% 0%,100% 100%,0% 100%)",
      "position": "center 30%",
      "placement": "bottom"
    }
  ],
  "categories" : [
      {
          "title" : "Daivaradhane",
          "items" : [
              {
                  "title" : "Title1",
                  "image" : "/assets/Explore/daivaradhane.jpg",
                  "alt" : "Daivaradhane",
                  "content" : "content1"
              },
              {
                  "title" : "Title1",
                  "image" : "/assets/Explore/daivaradhane.jpg",
                  "alt" : "Daivaradhane",
                  "content" : "content1"
              },
              {
                  "title" : "Title1",
                  "image" : "/assets/Explore/daivaradhane.jpg",
                  "alt" : "Daivaradhane",
                  "content" : "content1"
              },
              {
                  "title" : "Title1",
                  "image" : "/assets/Explore/daivaradhane.jpg",
                  "alt" : "Daivaradhane",
                  "content" : "content1"
              },
              {
                  "title" : "Title1",
                  "image" : "/assets/Explore/daivaradhane.jpg",
                  "alt" : "Daivaradhane",
                  "content" : "content1"
              },
              {
                  "title" : "Title1",
                  "image" : "/assets/Explore/daivaradhane.jpg",
                  "alt" : "Daivaradhane",
                  "content" : "content1"
              },
              {
                  "title" : "Title1",
                  "image" : "/assets/Explore/daivaradhane.jpg",
                  "alt" : "Daivaradhane",
                  "content" : "content1"
              },
              {
                  "title" : "Title1",
                  "image" : "/assets/Explore/daivaradhane.jpg",
                  "alt" : "Daivaradhane",
                  "content" : "content1"
              },
              {
                  "title" : "Title1",
                  "image" : "/assets/Explore/daivaradhane.jpg",
                  "alt" : "Daivaradhane",
                  "content" : "content1"
              },
              {
                  "title" : "Title1",
                  "image" : "/assets/Explore/daivaradhane.jpg",
                  "alt" : "Daivaradhane",
                  "content" : "content1"
              },
              {
                  "title" : "Title1",
                  "image" : "/assets/Explore/daivaradhane.jpg",
                  "alt" : "Daivaradhane",
                  "content" : "content1"
              },
              {
                  "title" : "Title1",
                  "image" : "/assets/Explore/daivaradhane.jpg",
                  "alt" : "Daivaradhane",
                  "content" : "content1"
              },
              {
                  "title" : "Title1",
                  "image" : "/assets/Explore/daivaradhane.jpg",
                  "alt" : "Daivaradhane",
                  "content" : "content1"
              },
              {
                  "title" : "Title1",
                  "image" : "/assets/Explore/daivaradhane.jpg",
                  "alt" : "Daivaradhane",
                  "content" : "content1"
              },
              {
                  "title" : "Title1",
                  "image" : "/assets/Explore/daivaradhane.jpg",
                  "alt" : "Daivaradhane",
                  "content" : "content1"
              }
            ]
        }
    ]
}
